pytkUI/__init__.py
pytkUI/boot_utils.py
pytkUI/locale_zh_cn.py
pytkUI/utils.py
pytkUI/widgets.py
pytkUI/__pyinstaller/__init__.py
pytkUI/__pyinstaller/hook-pytkUI.py
pytkUI/ext/__init__.py
pytkUI/ext/ext_tabs.py
pytkUI/ext/icon.py
pytkUI/ext/time_picker.py
pytkUI/ext/time_picker_dialog.py
pytkUI/icons/__init__.py
pytkUI/icons/bootstrap-icons.json
pytkUI/icons/bootstrap-icons.woff
pytkUI/overwrite/__init__.py
pytkUI-1.3.5.dist-info/METADATA
pytkUI-1.3.5.dist-info/WHEEL
pytkUI-1.3.5.dist-info/entry_points.txt
pytkUI-1.3.5.dist-info/top_level.txt
pytkUI-1.3.5.dist-info/RECORD
