Metadata-Version: 2.1
Name: pytkUI
Version: 1.3.5
Summary: TkinterHelper布局助手官方拓展和工具库
Home-page: https://www.pytk.net
Author: iamxcd
